README.md
setup.py
xdict/__init__.py
xdict/block.py
xdict/cmdline.py
xdict/escape.py
xdict/fmt_jstr.py
xdict/fsm.py
xdict/get_jdict_token_set.py
xdict/hdict_object.py
xdict/hdict_xml.py
xdict/ide.py
xdict/jprint.py
xdict/jprint_help.py
xdict/jsfunc.py
xdict/prepare_quotes_token_machine.py
xdict/quote.py
xdict/regextool.py
xdict/tokenize_block.py
xdict/tokenize_quotes.py
xdict/utils.py
xdict.egg-info/PKG-INFO
xdict.egg-info/SOURCES.txt
xdict.egg-info/dependency_links.txt
xdict.egg-info/entry_points.txt
xdict.egg-info/top_level.txt
xdict/CrtableLib/__init__.py
xdict/CrtableLib/crtable.py
xdict/CrtableLib/crtable.tst.py
xdict/HdictLib/__init__.py
xdict/HdictLib/hdict.py
xdict/TestLib/__init__.py
xdict/TestLib/genrand.py
xdict/bin/__init__.py
xdict/bin/creat_apis_from_strblk.py
xdict/bin/creat_apis_from_verb.py
xdict/bin/hentry.py
xdict/bin/ide_indent.py
xdict/bin/jsonq.py
xdict/bin/pobj.py